yta_video_base/__init__.py
yta_video_base/frame/__init__.py
yta_video_base/frame/mask/__init__.py
yta_video_base/parser.py
yta_video_base/video/__init__.py
yta_video_base/video/attribute_modifier.py
yta_video_base/video/setting.py
yta_video_base/video/validation.py
yta_video_base-0.0.23.dist-info/licenses/LICENSE
yta_video_base-0.0.23.dist-info/METADATA
yta_video_base-0.0.23.dist-info/WHEEL
yta_video_base-0.0.23.dist-info/RECORD
