Metadata-Version: 2.4
Name: yta-video-base
Version: 0.0.23
Summary: Youtube Autonomous Video Base Module.
License-File: LICENSE
Author: danialcala94
Author-email: danielalcalavalera@gmail.com
Requires-Python: ==3.9
Classifier: Programming Language :: Python :: 3
Classifier: Programming Language :: Python :: 3.9
Requires-Dist: moviepy (>=0.0.1,<9.0.0)
Requires-Dist: numpy (>=0.0.1,<9.0.0)
Requires-Dist: yta_file (>=0.0.1,<1.0.0)
Requires-Dist: yta_general_utils (>=0.0.1,<1.0.0)
Requires-Dist: yta_validation (>=0.0.1,<1.0.0)
Requires-Dist: yta_video_editor (>=0.0.1,<1.0.0)
Requires-Dist: yta_video_frame_time (>=0.0.1,<1.0.0)
Requires-Dist: yta_video_moviepy (>=0.0.1,<1.0.0)
